{"chunk_definitions":[{"row":29,"row_count":1,"visible":true,"expansion_state":0,"options":{"engine":"r","label":"setup","include":false},"document_id":"9D51C554","chunk_id":"csetup_chunk","chunk_label":"setup"},{"row":63,"row_count":1,"visible":true,"expansion_state":0,"options":{"engine":"r","label":"unnamed-chunk-15"},"document_id":"CCD4C7B1","chunk_id":"cklo9ay03afyu","chunk_label":"unnamed-chunk-1"},{"row":69,"row_count":1,"visible":true,"expansion_state":0,"options":{"engine":"r","label":"unnamed-chunk-16"},"document_id":"9D51C554","chunk_id":"ckni2wsxvl422","chunk_label":"unnamed-chunk-2"},{"row":78,"row_count":1,"visible":true,"expansion_state":0,"options":{"engine":"r","label":"unnamed-chunk-17"},"document_id":"9D51C554","chunk_id":"cphf7kszdx2s4","chunk_label":"unnamed-chunk-3"},{"row":116,"row_count":1,"visible":true,"expansion_state":0,"options":{"engine":"r","label":"unnamed-chunk-18"},"document_id":"9D51C554","chunk_id":"cu50eifc4hcyu","chunk_label":"unnamed-chunk-5"},{"row":133,"row_count":1,"visible":true,"expansion_state":0,"options":{"engine":"r","label":"unnamed-chunk-19"},"document_id":"9D51C554","chunk_id":"ce2zvlbvsd9py","chunk_label":"unnamed-chunk-6"},{"row":154,"row_count":1,"visible":true,"expansion_state":0,"options":{"engine":"r","label":"unnamed-chunk-20"},"document_id":"9D51C554","chunk_id":"ce8n5b3t55lzd","chunk_label":"unnamed-chunk-7"},{"row":172,"row_count":1,"visible":true,"expansion_state":0,"options":{"engine":"r","label":"unnamed-chunk-21"},"document_id":"9D51C554","chunk_id":"ch1r3c0pkbrli","chunk_label":"unnamed-chunk-8"},{"row":190,"row_count":1,"visible":true,"expansion_state":0,"options":{"engine":"r","label":"unnamed-chunk-22"},"document_id":"9D51C554","chunk_id":"crpi9cl354rnx","chunk_label":"unnamed-chunk-9"},{"row":204,"row_count":1,"visible":true,"expansion_state":0,"options":{"engine":"r","label":"unnamed-chunk-23"},"document_id":"9D51C554","chunk_id":"c4h86aot6306f","chunk_label":"unnamed-chunk-10"},{"row":245,"row_count":1,"visible":true,"expansion_state":0,"options":{"engine":"r","label":"unnamed-chunk-24"},"document_id":"9D51C554","chunk_id":"ccpkxhgjbud3e","chunk_label":"unnamed-chunk-12"},{"row":262,"row_count":1,"visible":true,"expansion_state":0,"options":{"engine":"r","label":"unnamed-chunk-25"},"document_id":"CCD4C7B1","chunk_id":"c7kly9dc0yr1i","chunk_label":"unnamed-chunk-13"},{"row":273,"row_count":1,"visible":true,"expansion_state":1,"options":{"engine":"r","label":"unnamed-chunk-12"},"document_id":"9D51C554","chunk_id":"cfvd1dvgk77r2","chunk_label":"unnamed-chunk-14"},{"row":296,"row_count":1,"visible":true,"expansion_state":0,"options":{"engine":"r","label":"unnamed-chunk-29"},"document_id":"CCD4C7B1","chunk_id":"csdjifwqd05kp","chunk_label":"unnamed-chunk-15"},{"row":315,"row_count":1,"visible":true,"expansion_state":0,"options":{"engine":"r","label":"unnamed-chunk-30"},"document_id":"9D51C554","chunk_id":"cww2n8cpoaomz","chunk_label":"unnamed-chunk-16"},{"row":326,"row_count":1,"visible":true,"expansion_state":0,"options":{},"document_id":"9D51C554","chunk_id":"ce4u8qy8chm03","chunk_label":"unnamed-chunk-17"}],"doc_write_time":1675951271,"working_dir":null,"default_chunk_options":{"tidy":false,"size":"small"},"chunk_rendered_width":700}